brawlapi/__init__.py
brawlapi_py-1.0.dist-info/METADATA
brawlapi_py-1.0.dist-info/WHEEL
brawlapi_py-1.0.dist-info/top_level.txt
brawlapi_py-1.0.dist-info/RECORD
