Metadata-Version: 2.1
Name: brawlapi-py
Version: 1.0
Summary: Simple python wrapper for the Brawl Stars API!
Home-page: https://github.com/Roma4ka-RedBad/brawlapi
Author: RomaDev
Author-email: 
License: UNKNOWN
Platform: UNKNOWN
Classifier: Programming Language :: Python :: 3
Classifier: License :: OSI Approved :: MIT License
Classifier: Operating System :: OS Independent
Requires-Python: >=3.6
